nonebot_JmDownloader/__init__.py
nonebot_JmDownloader/kooks/__init__.py
nonebot_JmDownloader-0.1.1.dist-info/METADATA
nonebot_JmDownloader-0.1.1.dist-info/WHEEL
nonebot_JmDownloader-0.1.1.dist-info/top_level.txt
nonebot_JmDownloader-0.1.1.dist-info/RECORD
